droplets/__init__.py
droplets/_version.py
droplets/droplet_tracks.py
droplets/droplets.py
droplets/emulsions.py
droplets/image_analysis.py
droplets/py.typed
droplets/trackers.py
droplets/resources/make_spheres_3d.py
droplets/resources/requirements.txt
droplets/resources/spheres_3d.hdf5
droplets/tools/__init__.py
droplets/tools/misc.py
droplets/tools/spherical.py
droplets/tools/typing.py
py_droplets-0.26.0.dist-info/licenses/LICENSE
py_droplets-0.26.0.dist-info/METADATA
py_droplets-0.26.0.dist-info/WHEEL
py_droplets-0.26.0.dist-info/top_level.txt
py_droplets-0.26.0.dist-info/RECORD
