Metadata-Version: 2.4
Name: py-droplets
Version: 0.26.0
Summary: Python package for describing and analyzing droplets in experiments and simulations
Author-email: David Zwicker <david.zwicker@ds.mpg.de>
License: MIT
Project-URL: homepage, https://github.com/zwicker-group/py-droplets
Project-URL: documentation, http://py-droplets.readthedocs.io
Project-URL: repository, https://github.com/zwicker-group/py-droplets
Keywords: emulsions,image-analysis
Classifier: Development Status :: 4 - Beta
Classifier: Intended Audience :: Developers
Classifier: Intended Audience :: Science/Research
Classifier: Topic :: Scientific/Engineering
Classifier: License :: OSI Approved :: MIT License
Classifier: Programming Language :: Python :: 3
Classifier: Programming Language :: Python :: 3.10
Classifier: Programming Language :: Python :: 3.11
Classifier: Programming Language :: Python :: 3.12
Classifier: Programming Language :: Python :: 3.13
Classifier: Programming Language :: Python :: 3.14
Requires-Python: <3.15,>=3.10
License-File: LICENSE
Requires-Dist: h5py>=2.10
Requires-Dist: matplotlib>=3.1
Requires-Dist: numba>=0.59
Requires-Dist: numpy>=1.22
Requires-Dist: scipy>=1.4
Requires-Dist: py-pde>=0.50
Requires-Dist: typing_extensions>=4
Dynamic: license-file
